agents_arcade/__init__.py
agents_arcade/_utils.py
agents_arcade/errors.py
agents_arcade/tools.py
agents_arcade-0.0.4.dist-info/METADATA
agents_arcade-0.0.4.dist-info/WHEEL
agents_arcade-0.0.4.dist-info/licenses/LICENSE
agents_arcade-0.0.4.dist-info/RECORD
