Metadata-Version: 2.4
Name: agents-arcade
Version: 0.0.4
Summary: Arcade Integration for OpenAI Agents
Project-URL: Homepage, https://github.com/ArcadeAI/agents-arcade
Project-URL: Repository, https://github.com/ArcadeAI/agents-arcade
Author-email: ArcadeAI <dev@arcade.dev>
License-Expression: MIT
License-File: LICENSE
Classifier: Intended Audience :: Developers
Classifier: License :: OSI Approved :: MIT License
Classifier: Operating System :: OS Independent
Classifier: Programming Language :: Python :: 3
Classifier: Programming Language :: Python :: 3.10
Classifier: Programming Language :: Python :: 3.11
Classifier: Programming Language :: Python :: 3.12
Classifier: Topic :: Software Development :: Libraries :: Python Modules
Classifier: Typing :: Typed
Requires-Python: >=3.9
Requires-Dist: arcadepy>=1.3.0
Requires-Dist: openai-agents>=0.0.4
